spips/__init__.py
spips/auto_reload.py
spips/cli.py
spips/spips.py
spips-0.2.7.dist-info/METADATA
spips-0.2.7.dist-info/WHEEL
spips-0.2.7.dist-info/entry_points.txt
spips-0.2.7.dist-info/top_level.txt
spips-0.2.7.dist-info/RECORD
