Metadata-Version: 2.1
Name: spips
Version: 0.2.7
Summary: spips a framework for python
Requires-Dist: colorama
Requires-Dist: watchdog
